labguru_api_client/__init__.py
labguru_api_client/api/__init__.py
labguru_api_client/api/antibodies/__init__.py
labguru_api_client/api/antibodies/get_api_v1_antibodies.py
labguru_api_client/api/antibodies/get_api_v1_antibodies_id.py
labguru_api_client/api/antibodies/post_api_v1_antibodies.py
labguru_api_client/api/antibodies/put_api_v1_antibodies_id.py
labguru_api_client/api/attachments/__init__.py
labguru_api_client/api/attachments/get_api_v1_attachments_id.py
labguru_api_client/api/attachments/post_api_v1_attachments.py
labguru_api_client/api/attachments/put_api_v1_attachments_id.py
labguru_api_client/api/authentication/__init__.py
labguru_api_client/api/authentication/post_api_v1_sessions.py
labguru_api_client/api/bacteria/__init__.py
labguru_api_client/api/bacteria/get_api_v1_bacteria.py
labguru_api_client/api/bacteria/get_api_v1_bacteria_id.py
labguru_api_client/api/bacteria/post_api_v1_bacteria.py
labguru_api_client/api/bacteria/put_api_v1_bacteria_id.py
labguru_api_client/api/boxes/__init__.py
labguru_api_client/api/boxes/get_api_v1_boxes.py
labguru_api_client/api/boxes/get_api_v1_boxes_id.py
labguru_api_client/api/boxes/post_api_v1_boxes.py
labguru_api_client/api/boxes/put_api_v1_boxes_id.py
labguru_api_client/api/cell_lines/__init__.py
labguru_api_client/api/cell_lines/get_api_v1_cell_lines.py
labguru_api_client/api/cell_lines/get_api_v1_cell_lines_id.py
labguru_api_client/api/cell_lines/post_api_v1_cell_lines.py
labguru_api_client/api/cell_lines/put_api_v1_cell_lines_id.py
labguru_api_client/api/comments/__init__.py
labguru_api_client/api/comments/get_api_v1_comments.py
labguru_api_client/api/comments/get_api_v1_comments_id.py
labguru_api_client/api/comments/post_api_v1_comments.py
labguru_api_client/api/companies/__init__.py
labguru_api_client/api/companies/get_api_v1_companies.py
labguru_api_client/api/companies/get_api_v1_companies_id.py
labguru_api_client/api/companies/post_api_v1_companies.py
labguru_api_client-0.1.3.dist-info/LICENSE
labguru_api_client-0.1.3.dist-info/METADATA
labguru_api_client-0.1.3.dist-info/WHEEL
labguru_api_client-0.1.3.dist-info/RECORD
